outline/__init__.py
outline/settings.py
outline/urls.py
outline/wsgi.py
outline/manage_outline.py
outline/apps/__init__.py
outline/static/placeholder.deleteme
outline/static/css/materialize.css
outline/static/css/font-awesome.min.css
outline/static/css/style.css
outline/static/css/materialize.min.css
outline/static/fonts/fontawesome-webfont.svg
outline/static/fonts/fontawesome-webfont.eot
outline/static/fonts/fontawesome-webfont.ttf
outline/static/fonts/FontAwesome.otf
outline/static/fonts/fontawesome-webfont.woff
outline/static/img/project6.jpeg
outline/static/img/avatar3.png
outline/static/img/parallax1.png
outline/static/img/avatar1.png
outline/static/img/avatar2.png
outline/static/img/project4.jpg
outline/static/img/avatar4.png
outline/static/img/project3.png
outline/static/img/project2.jpeg
outline/static/img/project5.png
outline/static/img/project1.jpg
outline/static/font/roboto/Roboto-Thin.ttf
outline/static/font/roboto/Roboto-Regular.ttf
outline/static/font/roboto/Roboto-Light.ttf
outline/static/font/roboto/Roboto-Medium.ttf
outline/static/font/roboto/Roboto-Bold.ttf
outline/static/font/material-design-icons/Material-Design-Icons.svg
outline/static/font/material-design-icons/Material-Design-Icons.eot
outline/static/font/material-design-icons/LICENSE.txt
outline/static/font/material-design-icons/Material-Design-Icons.ttf
outline/static/font/material-design-icons/Material-Design-Icons.woff
outline/static/js/init.js
outline/static/js/materialize.js
outline/static/js/materialize.min.js
outline/static/js/modernizr.js
outline/templates/homepage.html
outline/templates/base.html
outline/templates/openid/login.html
outline/templates/openid/base.html
outline-4.0.0.dist-info/METADATA
outline-4.0.0.dist-info/entry_points.txt
outline-4.0.0.dist-info/metadata.json
outline-4.0.0.dist-info/DESCRIPTION.rst
outline-4.0.0.dist-info/RECORD
outline-4.0.0.dist-info/top_level.txt
outline-4.0.0.dist-info/WHEEL
