Metadata-Version: 2.0
Name: outline
Version: 4.0.0
Summary: An outline for django applications.
Home-page: http://github.com/powellc/outline
Author: Colin Powell
Author-email: colin.powell@gmail.com
License: BSD
Platform: OS Independent
Classifier: Development Status :: 4 - Beta
Classifier: Framework :: Django
Classifier: Intended Audience :: Developers
Classifier: License :: OSI Approved :: BSD License
Classifier: Operating System :: OS Independent
Classifier: Programming Language :: Python
Classifier: Topic :: Internet :: WWW/HTTP
Classifier: Topic :: Internet :: WWW/HTTP :: Dynamic Content
Requires-Dist: Django (>=1.10,<1.11)
Requires-Dist: django-configurations (>=1.0)
Requires-Dist: dj-database-url (>=0.3.0)
Requires-Dist: pylibmc (>=1.5.0)
Requires-Dist: Pillow (>=3.0.0)
Requires-Dist: django-cache-url (>=0.8.0)
Requires-Dist: werkzeug (>=0.9.4)
Requires-Dist: gunicorn (>=0.19.4)
Requires-Dist: easy-thumbnails (>=1.2)
Requires-Dist: django-debug-toolbar (>=1.7)
Requires-Dist: django-extensions (>=1.6.1)
Requires-Dist: django-braces (>=1.4.0)
Requires-Dist: django-localflavor (>=1.1)
Requires-Dist: django-allauth (>=0.24.1)
Requires-Dist: django-floppyforms (>=1.6.1)
Requires-Dist: django-custom-user (>=0.5)
Requires-Dist: django-nose (>=1.4.1)
Requires-Dist: raven (>=5.2.0)
Requires-Dist: factory-boy (>=2.5.1)
Requires-Dist: boto (>=2.39.0)
Requires-Dist: django-storages (>=1.1.8)
Requires-Dist: djangorestframework (>=3.3.2)
Requires-Dist: django-cors-headers (>=1.1.0)
Requires-Dist: markdown (>=2.6.1)
Requires-Dist: django-filter (>=0.9.2)
Requires-Dist: django-templated-email (>=0.4.9)
